MANIFEST.in
RELEASE-VERSION
pavement.py
paver-minilib.zip
setup.py
version.py
protobuf_helpers/__init__.py
protobuf_helpers.egg-info/PKG-INFO
protobuf_helpers.egg-info/SOURCES.txt
protobuf_helpers.egg-info/dependency_links.txt
protobuf_helpers.egg-info/requires.txt
protobuf_helpers.egg-info/top_level.txt
protobuf_helpers/bin/protoc.exe
protobuf_helpers/bin/readme.txt