Metadata-Version: 1.0
Name: protobuf-helpers
Version: 0.3
Summary: Helper functions and classes for the `protobuf` package, providing, e.g., automatic generation of RPC message types based on a C++ class definition from a header file.
Home-page: https://github.com/wheeler-microfluidics/protobuf_helpers
Author: Christian Fobel
Author-email: UNKNOWN
License: GPL
Keywords: c++ clang introspection protobuf rpc
Platform: UNKNOWN
